hopla/__init__.py
hopla/__main__.py
hopla/kickstart.py
hopla/cli/__init__.py
hopla/cli/authenticate.py
hopla/cli/cast.py
hopla/cli/complete.py
hopla/cli/config.py
hopla/cli/feed.py
hopla/cli/feed_all.py
hopla/cli/get_group.py
hopla/cli/hatch_all.py
hopla/cli/request.py
hopla/cli/support_development.py
hopla/cli/version.py
hopla/cli/add/__init__.py
hopla/cli/add/todo.py
hopla/cli/buy/__init__.py
hopla/cli/buy/enchanted_armoire.py
hopla/cli/get_user/__init__.py
hopla/cli/get_user/auth.py
hopla/cli/get_user/info.py
hopla/cli/get_user/inventory.py
hopla/cli/get_user/stats.py
hopla/cli/groupcmds/__init__.py
hopla/cli/groupcmds/add.py
hopla/cli/groupcmds/api.py
hopla/cli/groupcmds/buy.py
hopla/cli/groupcmds/get_user.py
hopla/cli/groupcmds/hatch.py
hopla/cli/groupcmds/set.py
hopla/cli/hatch/__init__.py
hopla/cli/hatch/quest_egg.py
hopla/cli/hatch/standard_egg.py
hopla/hoplalib/__init__.py
hopla/hoplalib/authorization.py
hopla/hoplalib/common.py
hopla/hoplalib/configuration.py
hopla/hoplalib/errors.py
hopla/hoplalib/hopla_option.py
hopla/hoplalib/hoplaversion.py
hopla/hoplalib/http.py
hopla/hoplalib/outputformatter.py
hopla/hoplalib/requests_helper.py
hopla/hoplalib/throttling.py
hopla/hoplalib/buy/__init__.py
hopla/hoplalib/buy/buy_controllers.py
hopla/hoplalib/cast/__init__.py
hopla/hoplalib/cast/castcontroller.py
hopla/hoplalib/cast/spellmodel.py
hopla/hoplalib/hatchery/__init__.py
hopla/hoplalib/hatchery/egg_data.py
hopla/hoplalib/hatchery/eggmodels.py
hopla/hoplalib/hatchery/hatchalgorithms.py
hopla/hoplalib/hatchery/hatchcontroller.py
hopla/hoplalib/hatchery/hatchpotion_data.py
hopla/hoplalib/hatchery/hatchpotionmodels.py
hopla/hoplalib/tasks/__init__.py
hopla/hoplalib/tasks/taskcontroller.py
hopla/hoplalib/tasks/taskmodel.py
hopla/hoplalib/user/__init__.py
hopla/hoplalib/user/usercontroller.py
hopla/hoplalib/user/usermodels.py
hopla/hoplalib/zoo/__init__.py
hopla/hoplalib/zoo/feed_clickhelper.py
hopla/hoplalib/zoo/fooddata.py
hopla/hoplalib/zoo/foodmodels.py
hopla_cli-0.1.3a0.dist-info/METADATA
hopla_cli-0.1.3a0.dist-info/WHEEL
hopla_cli-0.1.3a0.dist-info/entry_points.txt
hopla_cli-0.1.3a0.dist-info/top_level.txt
hopla_cli-0.1.3a0.dist-info/RECORD
