Metadata-Version: 2.1
Name: hopla-cli
Version: 0.1.3a0
Summary: Hopla is a CLI to interact with the habitica.com API
Home-page: https://github.com/melvio/hopla
Author: melvio
Author-email: hopla.pypi@gmail.com
License: Apache-2.0
Project-URL: Source, https://github.com/melvio/hopla/
Project-URL: Readme, https://github.com/melvio/hopla/blob/main/README.md
Project-URL: License, https://github.com/melvio/hopla/blob/main/LICENSE
Project-URL: Issue Tracker, https://github.com/melvio/hopla/issues/
Project-URL: Stackoverflow Account, https://stackoverflow.com/users/12520740/melvio
Project-URL: Wiki, https://habitica.fandom.com/wiki/Hopla
Project-URL: PyPi, https://pypi.org/project/hopla-cli/
Keywords: cli,habitica,productivity,todo,tasks
Classifier: Intended Audience :: Developers
Classifier: License :: OSI Approved :: Apache Software License
Classifier: Environment :: Console
Classifier: Natural Language :: English
Classifier: Development Status :: 3 - Alpha
Classifier: Programming Language :: Python :: 3.8
Classifier: Programming Language :: Python :: 3.9
Classifier: Programming Language :: Python :: 3
Classifier: Programming Language :: Python :: 3 :: Only
Classifier: Operating System :: OS Independent
Classifier: Topic :: Utilities
Requires-Python: >=3.8
Requires-Dist: requests
Requires-Dist: Click
